bucktrix/__main__.py
bucktrix/callback.py
bucktrix/config.py
bucktrix/conn.py
bucktrix/task.py
bucktrix-0.1.5.dist-info/LICENSE
bucktrix-0.1.5.dist-info/WHEEL
bucktrix-0.1.5.dist-info/METADATA
bucktrix-0.1.5.dist-info/RECORD
