Metadata-Version: 2.1
Name: bucktrix
Version: 0.1.5
Summary: Matrix bot
Home-page: https://github.com/finzzz/bucktrix
Author: Vincent Carlos
Author-email: git@finzzz.net
Requires-Python: >=3.7,<4.0
Classifier: Programming Language :: Python :: 3
Classifier: Programming Language :: Python :: 3.7
Classifier: Programming Language :: Python :: 3.8
Classifier: Programming Language :: Python :: 3.9
Requires-Dist: matrix-nio[e2e] (>=0.16.0,<0.17.0)
